Metadata-Version: 2.1
Name: broonie
Version: 0.1.7
Summary: SVD PCA Projection Imputation Pipeline
Home-page: http://github.com/RENCI/broonie
Author: Jeffery Tilson
Author-email: jtilson@renci.org
License: UNKNOWN
Keywords: pca projection imputation pipeline batch corrected
Platform: Windows
Platform: Linux
Platform: Solaris
Platform: Mac OS-X
Platform: Unix
Classifier: Development Status :: 3 - Alpha
Classifier: Intended Audience :: Science/Research
Classifier: Intended Audience :: Developers
Classifier: Programming Language :: Python
Classifier: Programming Language :: Python :: 3
Classifier: Topic :: Software Development
Classifier: Topic :: Scientific/Engineering
Classifier: Operating System :: Unix
Classifier: Operating System :: POSIX :: Linux
Requires-Dist: markdown
Requires-Dist: matplotlib
Requires-Dist: numpy
Requires-Dist: pandas
Requires-Dist: scikit-learn
Requires-Dist: scipy
